blocksat_api/__init__.py
blocksat_api/blocksat.py
blocksat_api-1.0.0.dist-info/METADATA
blocksat_api-1.0.0.dist-info/WHEEL
blocksat_api-1.0.0.dist-info/top_level.txt
blocksat_api-1.0.0.dist-info/RECORD
