Metadata-Version: 2.1
Name: blocksat-api
Version: 1.0.0
Summary: Python bindings for Blocksat API
Home-page: https://github.com/willcl-ark/blockstream_blocksat
Author: Will Clark
Author-email: will8clark@gmail.com
License: UNKNOWN
Keywords: blockstream blocksat api
Platform: UNKNOWN
Classifier: Programming Language :: Python :: 3.6
Classifier: License :: OSI Approved :: MIT License
Classifier: Operating System :: OS Independent
Requires-Python: >=3.6
Requires-Dist: requests
